eyedentify3d/__init__.py
eyedentify3d/error_type.py
eyedentify3d/time_range.py
eyedentify3d/version.py
eyedentify3d/data_parsers/__init__.py
eyedentify3d/data_parsers/abstract_data.py
eyedentify3d/data_parsers/htc_vive_pro_data.py
eyedentify3d/data_parsers/meta_quest_pro_data.py
eyedentify3d/data_parsers/pupil_invisible_data.py
eyedentify3d/data_parsers/reduced_data.py
eyedentify3d/identification/__init__.py
eyedentify3d/identification/blink.py
eyedentify3d/identification/event.py
eyedentify3d/identification/fixation.py
eyedentify3d/identification/gaze_behavior_identifier.py
eyedentify3d/identification/inter_saccades.py
eyedentify3d/identification/invalid.py
eyedentify3d/identification/saccade.py
eyedentify3d/identification/smooth_pursuit.py
eyedentify3d/identification/visual_scanning.py
eyedentify3d/utils/__init__.py
eyedentify3d/utils/check_utils.py
eyedentify3d/utils/data_utils.py
eyedentify3d/utils/plot_utils.py
eyedentify3d/utils/rotation_utils.py
eyedentify3d/utils/sequence_utils.py
eyedentify3d/utils/signal_utils.py
eyedentify3d-1.0.4.dist-info/licenses/LICENSE
eyedentify3d-1.0.4.dist-info/METADATA
eyedentify3d-1.0.4.dist-info/WHEEL
eyedentify3d-1.0.4.dist-info/top_level.txt
eyedentify3d-1.0.4.dist-info/RECORD
