Metadata-Version: 2.4
Name: eyedentify3d
Version: 1.0.4
Summary: A package to identify gaze behavior from 3D eye-tracking data.
Home-page: https://github.com/EveCharbie/EyeDentify3D
Author: Eve Charbonneau
Author-email: EveCharbie <eve.charbie@gmail.com>
Project-URL: Documentation, https://github.com/EveCharbie/EyeDentify3d/tree/main#readme
Project-URL: Source, https://github.com/EveCharbie/EyeDentify3d
Project-URL: Tracker, https://github.com/EveCharbie/EyeDentify3d/issues
Classifier: License :: OSI Approved :: MIT License
Classifier: Programming Language :: Python
Requires-Python: >=3.11
License-File: LICENSE
Requires-Dist: scipy
Requires-Dist: numpy
Requires-Dist: matplotlib
Requires-Dist: pandas
Requires-Dist: pingouin
Provides-Extra: test
Requires-Dist: pytest; extra == "test"
Requires-Dist: black; extra == "test"
Dynamic: author
Dynamic: home-page
Dynamic: license-file
